LICENSE
MANIFEST.in
README.md
requirements.txt
setup.py
b64img/__init__.py
b64img.egg-info/PKG-INFO
b64img.egg-info/SOURCES.txt
b64img.egg-info/dependency_links.txt
b64img.egg-info/entry_points.txt
b64img.egg-info/requires.txt
b64img.egg-info/top_level.txt